tortoise-stubs/fields/__init__.pyi
tortoise-stubs/py.typed
tortoise_orm_stubs-1.0.2.dist-info/LICENSE
tortoise_orm_stubs-1.0.2.dist-info/WHEEL
tortoise_orm_stubs-1.0.2.dist-info/METADATA
tortoise_orm_stubs-1.0.2.dist-info/RECORD
