Metadata-Version: 2.1
Name: tortoise-orm-stubs
Version: 1.0.2
Summary: Type stubs that make tortoise-orm a lot easier to work with when using type checkers.
Home-page: https://github.com/zmievsa/tortoise-orm-stubs
License: MIT
Author: Stanislav Zmiev
Author-email: zmievsa@gmail.com
Requires-Python: >=3.8,<4.0
Classifier: License :: OSI Approved :: MIT License
Classifier: Programming Language :: Python :: 3
Classifier: Programming Language :: Python :: 3.8
Classifier: Programming Language :: Python :: 3.9
Classifier: Programming Language :: Python :: 3.10
Classifier: Programming Language :: Python :: 3.11
Requires-Dist: tortoise-orm
Project-URL: Repository, https://github.com/zmievsa/tortoise-orm-stubs
